pachca/__init__.py
pachca/exceptions.py
pachca/file.py
pachca/pachca.py
pachca-0.0.1.dist-info/METADATA
pachca-0.0.1.dist-info/WHEEL
pachca-0.0.1.dist-info/licenses/LICENSE
pachca-0.0.1.dist-info/RECORD
