Metadata-Version: 2.4
Name: pachca
Version: 0.0.1
Summary: Python API client for Pachca chat.
Project-URL: Homepage, https://github.com/ykoryakov/pachca
Project-URL: Issues, https://github.com/ykoryakov/pachca/issues
Author-email: Yury Koryakov <ykoryakov@yandex.ru>
License-Expression: Apache-2.0
License-File: LICENSE
Classifier: Operating System :: OS Independent
Classifier: Programming Language :: Python :: 3
Classifier: Programming Language :: Python :: 3.9
Classifier: Programming Language :: Python :: 3.10
Classifier: Programming Language :: Python :: 3.11
Classifier: Programming Language :: Python :: 3.12
Classifier: Programming Language :: Python :: 3.13
Requires-Python: >=3.9
Requires-Dist: requests
